{
  "schedules": [
    {
      "id": "1751432885021",
      "name": "Bruno",
      "when": "2025-07-02T22:00:00.000Z"
    },
    {
      "id": "1751775946166",
      "name": "Bruno",
      "when": "2025-07-06T21:00:00.000Z"
    },
    {
      "id": "1751776019771",
      "name": "Bruno",
      "when": "2025-07-06T23:00:00.000Z"
    },
    {
      "id": "1751944520486",
      "name": "Bruno",
      "when": "2025-07-08T21:00:00.000Z"
    },
    {
      "id": "1751944628847",
      "name": "Bruno",
      "when": "2025-07-08T15:00:00.000Z"
    },
    {
      "id": "1751945929975",
      "name": "Teste",
      "when": "2025-07-09T18:00:00.000Z"
    }
  ]
}